{
  "borderRadius": "0px",
  "bottomRow": 41,
  "boxShadow": "none",
  "dynamicBindingPathList": [],
  "dynamicHeight": "FIXED",
  "dynamicTriggerPathList": [],
  "fontFamily": "System Default",
  "fontSize": "0.875rem",
  "fontStyle": "BOLD",
  "isLoading": false,
  "isVisible": "true",
  "labelTextSize": "0.875rem",
  "leftColumn": 1,
  "maxDynamicHeight": 9000,
  "minDynamicHeight": 4,
  "overflow": "NONE",
  "parentColumnSpace": 7.15625,
  "parentId": "f6o5ujc94b",
  "parentRowSpace": 10,
  "rightColumn": 22,
  "text": "Interest Level:",
  "textAlign": "LEFT",
  "textColor": "#231F20",
  "topRow": 37,
  "type": "TEXT_WIDGET",
  "version": 1,
  "widgetId": "qcpva9v3j5",
  "widgetName": "col_text_1Copy"
}